{
  "?xml": {
    "@version": "1.0",
    "@encoding": "utf-8"
  },
  "ZWaveDevice": {
    "@xmlns": "http://www.pepper1.net/zwavedb/xml-schemata/z-wave",
    "@schemaVersion": "2",
    "descriptorVersion": "1",
    "deviceData": {
      "manufacturerId": {
        "@value": "0089"
      },
      "productType": {
        "@value": "0001"
      },
      "productId": {
        "@value": "0101"
      },
      "libType": {
        "@value": "04"
      },
      "protoVersion": {
        "@value": "02"
      },
      "protoSubVersion": {
        "@value": "33"
      },
      "appVersion": {
        "@value": "01"
      },
      "appSubVersion": {
        "@value": "02"
      },
      "basicClass": {
        "@value": "03"
      },
      "genericClass": {
        "@value": "10"
      },
      "specificClass": {
        "@value": "01"
      },
      "optional": {
        "@value": "true"
      },
      "listening": {
        "@value": "true"
      },
      "routing": {
        "@value": "true"
      },
      "beamSensor": "0",
      "rfFrequency": "EU",
      "certId": "13835",
      "certNumber": "ZC08-10040001"
    },
    "deviceDescription": {
      "description": {
        "lang": {
          "@xml:lang": "en",
          "#text": "Lighting Switch Module"
        }
      },
      "wakeupNote": {
        "lang": {
          "@xml:lang": "en"
        }
      },
      "inclusionNote": {
        "lang": {
          "@xml:lang": "en",
          "#text": "When prompted by your primary controller, press the\r\nbutton"
        }
      },
      "productName": "Switch Link",
      "brandName": "Easy Light",
      "productLine": "End Device",
      "productCode": "ZSL301EU",
      "productVersion": "1.00"
    },
    "commandClasses": {
      "commandClass": [
        {
          "@id": "0020",
          "@inNIF": "false"
        },
        {
          "@id": "0025"
        },
        {
          "@id": "0086"
        },
        {
          "@id": "0027"
        },
        {
          "@id": "002b"
        },
        {
          "@id": "002c"
        },
        {
          "@id": "0070"
        },
        {
          "@id": "0072"
        },
        {
          "@id": "0075"
        }
      ]
    },
    "configParams": {
      "configParam": [
        {
          "@number": "0",
          "@type": "constant",
          "@size": "1",
          "@default": "00",
          "name": {
            "lang": {
              "@xml:lang": "en",
              "#text": "Last Status"
            }
          },
          "description": {
            "lang": {
              "@xml:lang": "en"
            }
          },
          "value": [
            {
              "@from": "00",
              "@to": "00",
              "description": {
                "lang": {
                  "@xml:lang": "en",
                  "#text": "To enable the module to resume the last status\r\nbefore the AC power goes down."
                }
              }
            },
            {
              "@from": "01",
              "@to": "01",
              "description": {
                "lang": {
                  "@xml:lang": "en",
                  "#text": "To enable the module to always turn the lights\r\nON when the AC power goes up."
                }
              }
            },
            {
              "@from": "02",
              "@to": "02",
              "description": {
                "lang": {
                  "@xml:lang": "en",
                  "#text": "To enable the module to always turn the light\r\nOFF when AC power line goes up."
                }
              }
            }
          ]
        },
        {
          "@number": "1",
          "@type": "constant",
          "@size": "1",
          "@default": "01",
          "name": {
            "lang": {
              "@xml:lang": "en",
              "#text": "Night Light"
            }
          },
          "description": {
            "lang": {
              "@xml:lang": "en"
            }
          },
          "value": [
            {
              "@from": "00",
              "@to": "00",
              "description": {
                "lang": {
                  "@xml:lang": "en",
                  "#text": "When the light is turn ON, LED on the module is\r\nturn ON and vice versa."
                }
              }
            },
            {
              "@from": "01",
              "@to": "01",
              "description": {
                "lang": {
                  "@xml:lang": "en",
                  "#text": "When the light is turn ON, LED on the module is\r\nturn OFF and vice versa."
                }
              }
            }
          ]
        },
        {
          "@number": "2",
          "@type": "constant",
          "@size": "1",
          "@default": "01",
          "name": {
            "lang": {
              "@xml:lang": "en",
              "#text": "Enable LED"
            }
          },
          "description": {
            "lang": {
              "@xml:lang": "en"
            }
          },
          "value": [
            {
              "@from": "00",
              "@to": "00",
              "description": {
                "lang": {
                  "@xml:lang": "en",
                  "#text": "Disable LED."
                }
              }
            },
            {
              "@from": "01",
              "@to": "01",
              "description": {
                "lang": {
                  "@xml:lang": "en",
                  "#text": "Enable LED to operate according to night light\r\nparameter."
                }
              }
            }
          ]
        },
        {
          "@number": "3",
          "@type": "constant",
          "@size": "1",
          "@default": "ff",
          "name": {
            "lang": {
              "@xml:lang": "en",
              "#text": "Enable All ON/All OFF"
            }
          },
          "description": {
            "lang": {
              "@xml:lang": "en"
            }
          },
          "value": [
            {
              "@from": "00",
              "@to": "00",
              "description": {
                "lang": {
                  "@xml:lang": "en",
                  "#text": "Disable both All ON and All OFF command."
                }
              }
            },
            {
              "@from": "01",
              "@to": "01",
              "description": {
                "lang": {
                  "@xml:lang": "en",
                  "#text": "Enable only All OFF command."
                }
              }
            },
            {
              "@from": "02",
              "@to": "02",
              "description": {
                "lang": {
                  "@xml:lang": "en",
                  "#text": "Enable only All ON command."
                }
              }
            },
            {
              "@from": "ff",
              "@to": "ff",
              "description": {
                "lang": {
                  "@xml:lang": "en",
                  "#text": "Enable both All ON and All OFF command."
                }
              }
            }
          ]
        },
        {
          "@number": "4",
          "@type": "constant",
          "@size": "1",
          "@default": "00",
          "name": {
            "lang": {
              "@xml:lang": "en",
              "#text": "Button Protection"
            }
          },
          "description": {
            "lang": {
              "@xml:lang": "en"
            }
          },
          "value": [
            {
              "@from": "00",
              "@to": "00",
              "description": {
                "lang": {
                  "@xml:lang": "en",
                  "#text": "User can use button for ON/OFF manual control."
                }
              }
            },
            {
              "@from": "01",
              "@to": "01",
              "description": {
                "lang": {
                  "@xml:lang": "en",
                  "#text": "This setting value is used to protect a module\r\nagainst unintentional control. To operate a\r\nmanual control requires pressing button 3 times\r\nwithin 1.5 seconds, the light will toggle to the\r\nnext stage. The light will turn off instantly if it is\r\nbeing on before setting."
                }
              }
            },
            {
              "@from": "02",
              "@to": "02",
              "description": {
                "lang": {
                  "@xml:lang": "en",
                  "#text": "Disable button from manual control. The light\r\nwill turn off instantly if it is being on before\r\nsetting."
                }
              }
            }
          ]
        },
        {
          "@number": "5",
          "@type": "rangemapped",
          "@size": "1",
          "@default": "00",
          "name": {
            "lang": {
              "@xml:lang": "en",
              "#text": "Delay In Time"
            }
          },
          "description": {
            "lang": {
              "@xml:lang": "en"
            }
          },
          "value": [
            {
              "@from": "00",
              "@to": "00",
              "description": {
                "lang": {
                  "@xml:lang": "en",
                  "#text": "The light will be ON instantaneously once ON\r\ncommand is received."
                }
              }
            },
            {
              "@from": "01",
              "@to": "05",
              "description": {
                "lang": {
                  "@xml:lang": "en",
                  "#text": "The module will detain the ON process for 1-5\r\nseconds up to user preferences."
                }
              }
            }
          ]
        },
        {
          "@number": "6",
          "@type": "rangemapped",
          "@size": "1",
          "@default": "00",
          "name": {
            "lang": {
              "@xml:lang": "en",
              "#text": "Delay Out Time"
            }
          },
          "description": {
            "lang": {
              "@xml:lang": "en"
            }
          },
          "value": [
            {
              "@from": "00",
              "@to": "00",
              "description": {
                "lang": {
                  "@xml:lang": "en",
                  "#text": "The light will be OFF instantaneously once OFF\r\ncommand is received."
                }
              }
            },
            {
              "@from": "01",
              "@to": "05",
              "description": {
                "lang": {
                  "@xml:lang": "en",
                  "#text": "The module will detain the OFF process for 1-5\r\nseconds up to user preferences."
                }
              }
            }
          ]
        },
        {
          "@number": "255",
          "@type": "constant",
          "@size": "1",
          "@default": "01",
          "name": {
            "lang": {
              "@xml:lang": "en",
              "#text": "FACTORY DEFAULT"
            }
          },
          "description": {
            "lang": {
              "@xml:lang": "en",
              "#text": "Valid Values = Ignore configuration value\r\nThis command will reset the whole above command values to the\r\ndefault factory values"
            }
          }
        }
      ]
    },
    "resourceLinks": {
      "deviceImage": {
        "@url": "http://www.pepper1.net/zwavedb/uploads/resources/e65471eeca177c215cf0acf10b1457042cf9cd1e.jpg"
      }
    }
  }
}