{
  "?xml": {
    "@version": "1.0",
    "@encoding": "utf-8"
  },
  "ZWaveDevice": {
    "@xmlns": "http://www.pepper1.net/zwavedb/xml-schemata/z-wave",
    "@schemaVersion": "2",
    "descriptorVersion": "1",
    "deviceData": {
      "manufacturerId": {
        "@value": "010f"
      },
      "productType": {
        "@value": "0b00"
      },
      "productId": {
        "@value": "4001"
      },
      "libType": {
        "@value": "03"
      },
      "protoVersion": {
        "@value": "03"
      },
      "protoSubVersion": {
        "@value": "43"
      },
      "appVersion": {
        "@value": "19"
      },
      "appSubVersion": {
        "@value": "19"
      },
      "basicClass": {
        "@value": "04"
      },
      "genericClass": {
        "@value": "a1"
      },
      "specificClass": {
        "@value": "02"
      },
      "optional": {
        "@value": "true"
      },
      "listening": {
        "@value": "false"
      },
      "routing": {
        "@value": "true"
      },
      "beamSensor": "0"
    },
    "deviceDescription": {
      "description": {
        "lang": [
          {
            "@xml:lang": "de",
            "#text": "Überflutungssensor mit Neigungssensor und Manipulationsschutz"
          },
          {
            "@xml:lang": "en",
            "#text": "Flood Sensor with Temp and Tilt"
          },
          {
            "@xml:lang": "ru",
            "#text": "Датчик протечки со встроенным датчиком температуры и перемещения"
          }
        ]
      },
      "wakeupNote": {
        "lang": [
          {
            "@xml:lang": "de",
            "#text": "Dreifaches schnelles Drücken der TMP-Taste im Gehäuseinneren"
          },
          {
            "@xml:lang": "en",
            "#text": "Triple clicking the TMP-Button inside the case"
          },
          {
            "@xml:lang": "ru",
            "#text": "Тройное нажатие на кнопку TMP внутри корпуса"
          }
        ]
      },
      "inclusionNote": {
        "lang": [
          {
            "@xml:lang": "de",
            "#text": "Dreifaches schnelles Drücken der TMP-Taste im Gehäuseinneren"
          },
          {
            "@xml:lang": "en",
            "#text": "Triple clicking the TMP-Button inside the case"
          },
          {
            "@xml:lang": "ru",
            "#text": "Тройное нажатие на кнопку TMP внутри корпуса"
          }
        ]
      },
      "productName": "Flood Sensor FGFS-101",
      "brandName": "Fibaro",
      "productLine": "Sensors",
      "productCode": "FGFS-101",
      "productVersion": "25.25",
      "batteryType": "CR123A",
      "batteryCount": "1"
    },
    "commandClasses": {
      "commandClass": [
        {
          "@id": "0020",
          "@inNIF": "false"
        },
        {
          "@id": "0030"
        },
        {
          "@id": "0060",
          "@version": "3"
        },
        {
          "@id": "0070"
        },
        {
          "@id": "0072"
        },
        {
          "@id": "0080"
        },
        {
          "@id": "0084"
        },
        {
          "@id": "0085",
          "@version": "2"
        },
        {
          "@id": "0086"
        },
        {
          "@id": "008e",
          "@version": "2"
        },
        {
          "@id": "009c"
        }
      ]
    },
    "assocGroups": {
      "assocGroup": [
        {
          "@number": "1",
          "@maxNodes": "5",
          "description": {
            "lang": [
              {
                "@xml:lang": "de",
                "#text": "Flut Alarm mit BASIC Set Kommando"
              },
              {
                "@xml:lang": "en",
                "#text": "Flood Alarm with BASIC SET"
              },
              {
                "@xml:lang": "ru",
                "#text": "Для устройств управляемых датчиком протечки, отправляется BASIC SET или ALARM"
              }
            ]
          }
        },
        {
          "@number": "2",
          "@maxNodes": "5",
          "description": {
            "lang": [
              {
                "@xml:lang": "de",
                "#text": "Neigungssensor und Programmiertaster"
              },
              {
                "@xml:lang": "en",
                "#text": "Tilt Sensor alarm and TMP button events"
              },
              {
                "@xml:lang": "ru",
                "#text": "Для устройств управляемых при срабатывании кнопки TMP и при срабатывании датчика наклона, отправляется ALARM GENERIC "
              }
            ]
          }
        },
        {
          "@number": "3",
          "@maxNodes": "1",
          "description": {
            "lang": [
              {
                "@xml:lang": "de",
                "#text": "allgemeiner Statusreport"
              },
              {
                "@xml:lang": "en",
                "#text": "reports device status"
              },
              {
                "@xml:lang": "ru",
                "#text": "Для контроллера, которому будут отправляться отчеты о состоянии устройства"
              }
            ]
          }
        }
      ]
    },
    "configParams": {
      "configParam": [
        {
          "@number": "1",
          "@type": "range",
          "@size": "2",
          "@default": "0000",
          "name": {
            "lang": [
              {
                "@xml:lang": "de",
                "#text": "Alarm Abschalt-Verzögerung"
              },
              {
                "@xml:lang": "en",
                "#text": "Alarm cancellation delay"
              },
              {
                "@xml:lang": "ru",
                "#text": "Через какое время после устранения протечки отключать сигнал тревоги"
              }
            ]
          },
          "description": {
            "lang": [
              {
                "@xml:lang": "de",
                "#text": "Definiert wird die Verzögerungszeit, nach der der Alarm abgeschaltet wird, wenn das Flut wieder weg ist"
              },
              {
                "@xml:lang": "en",
                "#text": "Delays flood alarm cancelation for the device after flooding has ceased"
              },
              {
                "@xml:lang": "ru",
                "#text": "Определяет период времени в секундах, в течение которого датчик протечки будет отправлять сигнал тревоги после исчезновения внешних аварийных факторов. Датчик в течение этого времени будет отчитываться главному контроллеру сети о своем аварийном состоянии. Значение этого параметра не влияет на звуковые и световые сигналы оповещения, действие которых прекращается немедленно после исчезновения внешних аварийных факторов."
              }
            ]
          },
          "value": {
            "@from": "0000",
            "@to": "0e10",
            "@unit": "s",
            "description": {
              "lang": [
                {
                  "@xml:lang": "de",
                  "#text": "Verzögerung in Sekunden (jeweils 1s); 0 (keine Verzögerung, direkte Beendigung des Alarms)"
                },
                {
                  "@xml:lang": "en",
                  "#text": "delay in seconds (each 1s);\n0 (no delay, immediate alarm cancelation)"
                },
                {
                  "@xml:lang": "ru",
                  "#text": "в секундах, 0 - никогда"
                }
              ]
            }
          }
        },
        {
          "@number": "2",
          "@type": "rangemapped",
          "@size": "1",
          "@default": "03",
          "name": {
            "lang": [
              {
                "@xml:lang": "de",
                "#text": "Akustische und Optische Signale An/Aus bei Flut"
              },
              {
                "@xml:lang": "en",
                "#text": "Acoustic and visual signals On / Off in case of flooding"
              },
              {
                "@xml:lang": "ru",
                "#text": "Звуковое и световое оповещение ВКЛ/ВЫКЛ при протечки"
              }
            ]
          },
          "description": {
            "lang": [
              {
                "@xml:lang": "de",
                "#text": "legt fest, ob akustisches und/oder optisches Signal bei Flut aktiviert oder deaktiviert ist"
              },
              {
                "@xml:lang": "en",
                "#text": "parameter allows for LED indicator and acoustic alarm deactivation in case of\r\nflooding detection"
              },
              {
                "@xml:lang": "ru",
                "#text": "Этот параметр позволяет отключать звуковое и световое оповещения в случае обнаружения протечки. Изменение значения этого параметра позволяет увеличить срок службы батареи датчика. Его изменения не влияют на связь датчика с главным контроллером сети. Команды для устройств из групп ассоциаций, отчеты о состоянии и аварийных ситуациях по-прежнему будет отправляться."
              }
            ]
          },
          "value": [
            {
              "@from": "00",
              "@to": "00",
              "description": {
                "lang": [
                  {
                    "@xml:lang": "de",
                    "#text": "akustischer und optischer Alarm inaktiv"
                  },
                  {
                    "@xml:lang": "en",
                    "#text": "acoustic and visual alarms inactive"
                  },
                  {
                    "@xml:lang": "ru",
                    "#text": "звуковое и световое оповещения отключены"
                  }
                ]
              }
            },
            {
              "@from": "01",
              "@to": "01",
              "description": {
                "lang": [
                  {
                    "@xml:lang": "de",
                    "#text": "akustischer Alarm inaktiv, optischer Alarm aktiv"
                  },
                  {
                    "@xml:lang": "en",
                    "#text": "acoustic alarm inactive, visual alarm active"
                  },
                  {
                    "@xml:lang": "ru",
                    "#text": "звуковое оповещение отключено, световое оповещение включено"
                  }
                ]
              }
            },
            {
              "@from": "02",
              "@to": "02",
              "description": {
                "lang": [
                  {
                    "@xml:lang": "de",
                    "#text": "akustischer Alarm aktiv, optischer Alarm inaktiv"
                  },
                  {
                    "@xml:lang": "en",
                    "#text": "acoustic alarm active, visual alarm inactive"
                  },
                  {
                    "@xml:lang": "ru",
                    "#text": "звуковое оповещение включено, световое оповещение отключено"
                  }
                ]
              }
            },
            {
              "@from": "03",
              "@to": "03",
              "description": {
                "lang": [
                  {
                    "@xml:lang": "de",
                    "#text": "akustischer und optischer Alarm aktiv"
                  },
                  {
                    "@xml:lang": "en",
                    "#text": "acoustic and visual alarms active"
                  },
                  {
                    "@xml:lang": "ru",
                    "#text": "звуковое и световое оповещения включены"
                  }
                ]
              }
            }
          ]
        },
        {
          "@number": "5",
          "@type": "rangemapped",
          "@size": "1",
          "@default": "ff",
          "name": {
            "lang": [
              {
                "@xml:lang": "de",
                "#text": "Typ des Alarms für die 1. Assoziationsgruppe (Flut)"
              },
              {
                "@xml:lang": "en",
                "#text": "Type of alarm frame sent to 1-st association group (FLOOD)"
              },
              {
                "@xml:lang": "ru",
                "#text": "Тип сигнала тревоги для устройств из группы №1 (Протечка)"
              }
            ]
          },
          "description": {
            "lang": [
              {
                "@xml:lang": "de",
                "#text": "legt fest, welches Kommando vom Sensor bei Flut oder Flutende gesendet wird"
              },
              {
                "@xml:lang": "en",
                "#text": "parameter determines a type of command frame sent by the Sensor in case\r\nflooding has been detected or cancelled"
              },
              {
                "@xml:lang": "ru",
                "#text": "Параметр определяет тип сигнала тревоги, посылаемого датчиком в случае обнаружения протечки или его отмены."
              }
            ]
          },
          "value": [
            {
              "@from": "00",
              "@to": "00",
              "description": {
                "lang": [
                  {
                    "@xml:lang": "de",
                    "#text": "ALARM WATER command frame"
                  },
                  {
                    "@xml:lang": "en",
                    "#text": "ALARM WATER command frame"
                  },
                  {
                    "@xml:lang": "ru",
                    "#text": "ALARM WATER"
                  }
                ]
              }
            },
            {
              "@from": "ff",
              "@to": "ff",
              "description": {
                "lang": [
                  {
                    "@xml:lang": "de",
                    "#text": "BASIC SET command frame"
                  },
                  {
                    "@xml:lang": "en",
                    "#text": "BASIC SET command frame"
                  },
                  {
                    "@xml:lang": "ru",
                    "#text": "BASIС SET"
                  }
                ]
              }
            }
          ]
        },
        {
          "@number": "7",
          "@type": "range",
          "@size": "1",
          "@default": "63",
          "name": {
            "lang": [
              {
                "@xml:lang": "de",
                "#text": "prozentuales Niveau beim Senden an erste Assoziationsgruppe"
              },
              {
                "@xml:lang": "en",
                "#text": "Forced dimming level sent to 1-st association group devices"
              },
              {
                "@xml:lang": "ru",
                "#text": "Уровень диммирования/процент открытия жалюзи, отправляемый устройствам из группы №1"
              }
            ]
          },
          "description": {
            "lang": [
              {
                "@xml:lang": "de",
                "#text": "legt fest, welches Niveau ein Dimmer oder eine Jalousie beim Senden die erste Assoziationsgruppe erhält"
              },
              {
                "@xml:lang": "en",
                "#text": "Forced dimming level / roller blind opening level, when sending turn on /\r\nopen"
              },
              {
                "@xml:lang": "ru",
                "#text": "Значение 255 включит диммер на последний установленный уровень, значение 30 включит диммер на 30%."
              }
            ]
          },
          "value": [
            {
              "@from": "01",
              "@to": "63",
              "@unit": "%",
              "description": {
                "lang": [
                  {
                    "@xml:lang": "de",
                    "#text": "1-99"
                  },
                  {
                    "@xml:lang": "en",
                    "#text": "1-99"
                  },
                  {
                    "@xml:lang": "ru",
                    "#text": "1-99"
                  }
                ]
              }
            },
            {
              "@from": "ff",
              "@to": "ff",
              "description": {
                "lang": [
                  {
                    "@xml:lang": "de",
                    "#text": "Der Letzte Satz Ebene (255)\r\n"
                  },
                  {
                    "@xml:lang": "en",
                    "#text": "The last set level (255)"
                  },
                  {
                    "@xml:lang": "ru",
                    "#text": "Последний установленный уровень (255)"
                  }
                ]
              }
            }
          ]
        },
        {
          "@number": "9",
          "@type": "rangemapped",
          "@size": "1",
          "@default": "00",
          "name": {
            "lang": [
              {
                "@xml:lang": "de",
                "#text": "Aktivieren oder deaktivieren der Alarmmeldung nach Ende der Flut"
              },
              {
                "@xml:lang": "en",
                "#text": "Alarm cancelling or turning a device off (Basic) command frame deactivation"
              },
              {
                "@xml:lang": "ru",
                "#text": "Отмена “Отключение сигнала тревоги” или “Отправка команды ВЫКЛ” для устройств из группы №1"
              }
            ]
          },
          "description": {
            "lang": [
              {
                "@xml:lang": "de",
                "#text": "Blockiert oder lässt zu, dass die Alarmmeldung nach Flutende abgeschaltet wird"
              },
              {
                "@xml:lang": "en",
                "#text": "Allows for deactivating device turn off and alarm cancellation functions for the\r\ndevices assigned to 1-st association group"
              },
              {
                "@xml:lang": "ru",
                "#text": "Значение параметра, равное 0, приводит к отмене отправки сообщений  BASIC SET = 0 или ALARM WATER = 0. То есть, после возникновения аварийной ситуации устройство будет продолжать отправку сигнала тревоги даже, если все внешние аварийные факторы прекратили свое действие. Такой режим работы может быть в дальнейшем отключен через МЕНЮ, отмеченное зеленым светодиодом."
              }
            ]
          },
          "value": [
            {
              "@from": "00",
              "@to": "00",
              "description": {
                "lang": [
                  {
                    "@xml:lang": "de",
                    "#text": "Alarmbeendigung (Flut) inaktiv"
                  },
                  {
                    "@xml:lang": "en",
                    "#text": "Alarm (flooding) cancellation inactive"
                  },
                  {
                    "@xml:lang": "ru",
                    "#text": "Отмена сигнала тревоги не активна"
                  }
                ]
              }
            },
            {
              "@from": "01",
              "@to": "01",
              "description": {
                "lang": [
                  {
                    "@xml:lang": "de",
                    "#text": "Alarmbeendigung (Flut) aktiv"
                  },
                  {
                    "@xml:lang": "en",
                    "#text": "Alarm (flooding) cancellation active"
                  },
                  {
                    "@xml:lang": "ru",
                    "#text": "Отмена сигнала тревоги активна"
                  }
                ]
              }
            }
          ]
        },
        {
          "@number": "10",
          "@type": "range",
          "@size": "2",
          "@default": "012c",
          "name": {
            "lang": [
              {
                "@xml:lang": "de",
                "#text": "Temperatur Mess-Intervalle"
              },
              {
                "@xml:lang": "en",
                "#text": "Temperature measurement interval"
              },
              {
                "@xml:lang": "ru",
                "#text": "Период измерения температуры"
              }
            ]
          },
          "description": {
            "lang": [
              {
                "@xml:lang": "de",
                "#text": "Zeit-Intervalle, in Sekunden, zwischen den Temperaturmessungen"
              },
              {
                "@xml:lang": "en",
                "#text": "Time interval, in seconds, between consecutive temperature measurements"
              },
              {
                "@xml:lang": "ru",
                "#text": "Временной интервал, в секундах, через который будут проводиться измерения температуры воздуха внутренним температурным датчиком. Измеренное значение будет передано главному контроллеру сети в случае, если оно изменилось по сравнению с предыдущим на величину, большую, чем гистерезис (определяется параметром №12). Этот параметр определяет величину временного интервала, через который Fibaro Flood Sensor будет измерять температуру окружающего воздуха и уровень заряда батареи, а затем отправлять их значения на главный контроллер.\r\nЕсли измеренная температура отличается от измеренной ранее на величину большую, чем определяемая параметром №12 (например, P12 = 50, то есть, гистерезис равен 0.5°С), то на контроллер будет отправлено новое значение температуры. Если уровень заряда батареи изменяется, его новая величина отправляется на контроллер посредством отчета Battery Report.\r\nЗначение этого параметра чрезвычайно важно в режиме работы от батареек – больший период измерения означает менее частые сеансы связи, что увеличивает срок службы батареек.\r\nПосле последовательных НЕУДАВШЕЙСЯ и УДАВШЕЙСЯ попыток связи датчик переходит в режим ожидания."
              }
            ]
          },
          "value": {
            "@from": "0001",
            "@to": "7fff",
            "@unit": "s",
            "description": {
              "lang": [
                {
                  "@xml:lang": "de",
                  "#text": "Zeitintervall in Sekunden"
                },
                {
                  "@xml:lang": "en",
                  "#text": "Time interval in seconds"
                },
                {
                  "@xml:lang": "ru",
                  "#text": "В секундах"
                }
              ]
            }
          }
        },
        {
          "@number": "12",
          "@type": "range",
          "@size": "2",
          "@default": "0032",
          "name": {
            "lang": [
              {
                "@xml:lang": "de",
                "#text": "Temperatur Mess-Schaltschwelle"
              },
              {
                "@xml:lang": "en",
                "#text": "Temperature measurement hysteresis"
              },
              {
                "@xml:lang": "ru",
                "#text": "Отчет при изменении температуры на определенную величину (гистерезис)"
              }
            ]
          },
          "description": {
            "lang": [
              {
                "@xml:lang": "de",
                "#text": "definiert den Temperaturunterschied, bei dem ein Temperaturreport gesendet wird"
              },
              {
                "@xml:lang": "en",
                "#text": "Determines a minimum temperature change value (insensitivity level), resulting in\r\na temperature report being sent"
              },
              {
                "@xml:lang": "ru",
                "#text": "Этот параметр определяет величину температуры, при изменении на которую отправляется отчет главному контроллеру сети, в соответствии со значением параметра №10."
              }
            ]
          },
          "value": {
            "@from": "0001",
            "@to": "03e8",
            "@unit": "°C",
            "description": {
              "lang": [
                {
                  "@xml:lang": "de",
                  "#text": "alle 0,01°C;\n(standard 50 = 0,5°C)"
                },
                {
                  "@xml:lang": "en",
                  "#text": "each 0,01°C;\n(default 50 = 0,5°C)"
                },
                {
                  "@xml:lang": "ru",
                  "#text": "1 = 0,01°C\n(по умолчанию 50 = 0,5°C)"
                }
              ]
            }
          }
        },
        {
          "@number": "13",
          "@type": "rangemapped",
          "@size": "1",
          "@default": "00",
          "name": {
            "lang": [
              {
                "@xml:lang": "de",
                "#text": "Alarm BROADCAST"
              },
              {
                "@xml:lang": "en",
                "#text": "Alarm BROADCAST"
              },
              {
                "@xml:lang": "ru",
                "#text": "Широковещательный сигнал тревоги"
              }
            ]
          },
          "description": {
            "lang": [
              {
                "@xml:lang": "de",
                "#text": "Werte außer 0 führen zum Aussenden eines BROADCAST (mit höherer Priorität als alle anderen Sendungen) an alle Geräte in direkter Reichweite des Senders"
              },
              {
                "@xml:lang": "en",
                "#text": "Value other than 0 means alarms are sent in BROADCAST mode (with a priority\r\nover other communicates), to all devices within the Sensor’s range"
              },
              {
                "@xml:lang": "ru",
                "#text": "Значения параметра, отличное от 0,  означает, что все сигналы тревоги будут посылаться широковещательно (BROADCAST) всем устройствам в зоне действия радиосвязи датчика Fibaro Flood Sensor (с приоритетом над другими пересылаемыми сообщениями). "
              }
            ]
          },
          "value": [
            {
              "@from": "00",
              "@to": "00",
              "description": {
                "lang": [
                  {
                    "@xml:lang": "de",
                    "#text": "broadcasts inaktiv"
                  },
                  {
                    "@xml:lang": "en",
                    "#text": "broadcasts inactive"
                  },
                  {
                    "@xml:lang": "ru",
                    "#text": "широковещательные сообщения отключены"
                  }
                ]
              }
            },
            {
              "@from": "01",
              "@to": "01",
              "description": {
                "lang": [
                  {
                    "@xml:lang": "de",
                    "#text": "Flut (1. Assoziationsgruppe) broadcast aktiv; Schutzschalter (2. Assoziationsgruppe) broadcast inaktiv"
                  },
                  {
                    "@xml:lang": "en",
                    "#text": "flood (1-st Association Group) broadcast active; tamper (2-nd Association\nGroup) broadcast inactive"
                  },
                  {
                    "@xml:lang": "ru",
                    "#text": "широковещательное оповещение о затоплении (для группы №1) включено, широковещательное сообщения о сработке темпера (для группы №2) выключено"
                  }
                ]
              }
            },
            {
              "@from": "02",
              "@to": "02",
              "description": {
                "lang": [
                  {
                    "@xml:lang": "de",
                    "#text": "Flut broadcast inaktiv; Schutzschalter broadcast aktiv"
                  },
                  {
                    "@xml:lang": "en",
                    "#text": "flood broadcast inactive; tamper broadcast active"
                  },
                  {
                    "@xml:lang": "ru",
                    "#text": "широковещательное оповещение о затоплении выключено, широковещательное сообщения о сработке темпера включено"
                  }
                ]
              }
            },
            {
              "@from": "03",
              "@to": "03",
              "description": {
                "lang": [
                  {
                    "@xml:lang": "de",
                    "#text": "Flut broadcast aktiv; Schutzschalter broadcast aktiv"
                  },
                  {
                    "@xml:lang": "en",
                    "#text": "flood broadcast active; tamper broadcast active"
                  },
                  {
                    "@xml:lang": "ru",
                    "#text": "широковещательное оповещение о затоплении включено, широковещательное сообщения о сработке темпера включено"
                  }
                ]
              }
            }
          ]
        },
        {
          "@number": "50",
          "@type": "range",
          "@size": "2",
          "@default": "05dc",
          "name": {
            "lang": [
              {
                "@xml:lang": "de",
                "#text": "untere Temperatur-Alarm-Grenze"
              },
              {
                "@xml:lang": "en",
                "#text": "Low temperature alarm threshold"
              },
              {
                "@xml:lang": "ru",
                "#text": "Настройка нижней критичной границы температуры"
              }
            ]
          },
          "description": {
            "lang": [
              {
                "@xml:lang": "de",
                "#text": "Temperatur-Wert unter dem die Anzeige LED mit einstellbarer Farbe blinkt"
              },
              {
                "@xml:lang": "en",
                "#text": "parameter stores a temperature value, below which LED indicator blinks with\r\na definable colour"
              },
              {
                "@xml:lang": "ru",
                "#text": "Этот параметр определяет значение температуры, ниже которой светодиодный индикатор будет мигать цветом, определяющимся параметром №61. По умолчанию светодиодный индикатор мигает синим цветом."
              }
            ]
          },
          "value": {
            "@from": "d8f0",
            "@to": "2710",
            "@unit": "x0,01°C",
            "description": {
              "lang": [
                {
                  "@xml:lang": "de",
                  "#text": "Wert 1500 (15,00°C)"
                },
                {
                  "@xml:lang": "en",
                  "#text": "value 1500 (15,00°C)"
                },
                {
                  "@xml:lang": "ru",
                  "#text": "1 =  0.01°С (по умолчанию 1500 = 15,0 °C)"
                }
              ]
            }
          }
        },
        {
          "@number": "51",
          "@type": "range",
          "@size": "2",
          "@default": "0dac",
          "name": {
            "lang": [
              {
                "@xml:lang": "de",
                "#text": "obere Temperatur-Alarm-Grenze"
              },
              {
                "@xml:lang": "en",
                "#text": "High temperature alarm threshold"
              },
              {
                "@xml:lang": "ru",
                "#text": "Настройка верхней критичной границы температуры"
              }
            ]
          },
          "description": {
            "lang": [
              {
                "@xml:lang": "de",
                "#text": "Temperatur-Wert über dem die Anzeige LED mit einstellbarer Farbe blinkt"
              },
              {
                "@xml:lang": "en",
                "#text": "parameter stores a temperature value, above which LED indicator blinks with\r\na definable colour"
              },
              {
                "@xml:lang": "ru",
                "#text": "Этот параметр определяет значение температуры, выше которой светодиодный индикатор будет мигать цветом, определяющимся параметром №62. По умолчанию светодиодный индикатор мигает красным цветом."
              }
            ]
          },
          "value": {
            "@from": "d8f0",
            "@to": "2710",
            "@unit": "x0,01°C",
            "description": {
              "lang": [
                {
                  "@xml:lang": "de",
                  "#text": "Wert 3500 (35,0°C)"
                },
                {
                  "@xml:lang": "en",
                  "#text": "value 3500 (35,0°C)"
                },
                {
                  "@xml:lang": "ru",
                  "#text": "1 =  0.01°С (по умолчанию 3500 = 35,0 °C)"
                }
              ]
            }
          }
        },
        {
          "@number": "61",
          "@type": "range",
          "@size": "4",
          "@default": "000000ff",
          "name": {
            "lang": [
              {
                "@xml:lang": "de",
                "#text": "untere Temperatur-Alarm-Grenze LED Farbe"
              },
              {
                "@xml:lang": "en",
                "#text": "Low temperature alarm indicator LED colour"
              },
              {
                "@xml:lang": "ru",
                "#text": "Цвет светодиодного индикатора, предупреждающего о низкой температуре"
              }
            ]
          },
          "description": {
            "lang": [
              {
                "@xml:lang": "de",
                "#text": "Parameter speichert RGB Farbwert"
              },
              {
                "@xml:lang": "en",
                "#text": "Parameter stores RGB colour value"
              },
              {
                "@xml:lang": "ru",
                "#text": "Главный контроллер сети воспринимает цвет как сумму значений его компонент (в формате RGB). Каждому цвету при этом соответствует значение от 0 до 255. Пример: Цвет индикатора= 65536 * КРАСНЫЙ + 256 * ЗЕЛЕНЫЙ + СИНИЙ"
              }
            ]
          },
          "value": {
            "@from": "00000000",
            "@to": "00ffffff",
            "description": {
              "lang": [
                {
                  "@xml:lang": "de",
                  "#text": "255 (Blau 0x000000FF)"
                },
                {
                  "@xml:lang": "en",
                  "#text": "255 (blue 0x000000FF)\r\nColour:\r\nRed = 16711680\r\nGreen = 65280\r\nBlue = 255\r\nYellow = 16776960\r\nTurquoise = 65535\r\nOrange = 16750848\r\nWhite = 16777215\r\nLED indicator turned off = 0\r\n"
                },
                {
                  "@xml:lang": "ru",
                  "#text": "255 (синий 0x000000FF)"
                }
              ]
            }
          }
        },
        {
          "@number": "62",
          "@type": "range",
          "@size": "4",
          "@default": "00ff0000",
          "name": {
            "lang": [
              {
                "@xml:lang": "de",
                "#text": "obere Temperatur-Alarm-Grenze LED Farbe"
              },
              {
                "@xml:lang": "en",
                "#text": "High temperature alarm indicator LED colour"
              },
              {
                "@xml:lang": "ru",
                "#text": "Цвет сигнального индикатора, предупреждающего о высокой температуре"
              }
            ]
          },
          "description": {
            "lang": [
              {
                "@xml:lang": "de",
                "#text": "Parameter speichert RGB Farbwert"
              },
              {
                "@xml:lang": "en",
                "#text": "Parameter stores RGB colour value"
              },
              {
                "@xml:lang": "ru",
                "#text": "Главный контроллер сети воспринимает цвет как сумму значений его компонент (в формате RGB). Каждому цвету при этом соответствует значение от 0 до 255. Пример: Цвет индикатора= 65536 * КРАСНЫЙ + 256 * ЗЕЛЕНЫЙ + СИНИЙ"
              }
            ]
          },
          "value": {
            "@from": "00000000",
            "@to": "00ffffff",
            "description": {
              "lang": [
                {
                  "@xml:lang": "de",
                  "#text": "16711680 (Rot 0x00FF0000)"
                },
                {
                  "@xml:lang": "en",
                  "#text": "16711680 (red 0x00FF0000)\r\nColour:\r\nRed = 16711680\r\nGreen = 65280\r\nBlue = 255\r\nYellow = 16776960\r\nTurquoise = 65535\r\nOrange = 16750848\r\nWhite = 16777215\r\nLED indicator turned off = 0\r\n"
                },
                {
                  "@xml:lang": "ru",
                  "#text": "16711680 (красный 0x00FF0000)"
                }
              ]
            }
          }
        },
        {
          "@number": "63",
          "@type": "rangemapped",
          "@size": "1",
          "@default": "02",
          "name": {
            "lang": [
              {
                "@xml:lang": "de",
                "#text": "Festlegen der Anzeige LED Einstellungen"
              },
              {
                "@xml:lang": "en",
                "#text": "Managing a LED indicator under standard operation"
              },
              {
                "@xml:lang": "ru",
                "#text": "Управление светодиодным индикатором в стандартных условиях эксплуатации"
              }
            ]
          },
          "description": {
            "lang": [
              {
                "@xml:lang": "de",
                "#text": "Parameter legt die Funktion der Anzeige LED fest. Wert 0 deaktiviert die LED um Strom zu sparen"
              },
              {
                "@xml:lang": "en",
                "#text": "Parameter determines LED indicator’s operation. Set to 0 turns the indicator off,\r\nsaving a battery life"
              },
              {
                "@xml:lang": "ru",
                "#text": "Этот параметр определяет режим работы светодиодного индикатора. Если установить параметру значения «0», то светодиод отключится, сохраняя заряд батареи."
              }
            ]
          },
          "value": [
            {
              "@from": "00",
              "@to": "00",
              "description": {
                "lang": [
                  {
                    "@xml:lang": "de",
                    "#text": "LED Anzeige zeigt keine Temperatur an"
                  },
                  {
                    "@xml:lang": "en",
                    "#text": "LED indicator doesn’t indicate the temperature"
                  },
                  {
                    "@xml:lang": "ru",
                    "#text": "Светодиодный индикатор не отображает температуру"
                  }
                ]
              }
            },
            {
              "@from": "01",
              "@to": "01",
              "description": {
                "lang": [
                  {
                    "@xml:lang": "de",
                    "#text": "LED Anzeige zeigt die Temperatur und blinkt bei jeder Temperatur-Messung (Parameter 10, Netzbetrieb und Batteriebetrieb) oder Wake Up Interval (Batteriebetrieb)"
                  },
                  {
                    "@xml:lang": "en",
                    "#text": "LED indicator indicates the temperature (blink) every Temperature\nMeasurement Interval (Parameter 10, constant current and battery) or Wake\nUp Interval (battery mode)"
                  },
                  {
                    "@xml:lang": "ru",
                    "#text": "Светодиодный индикатор отображает температуру (мигает) на каждом интервале измерения температуры (параметр №10, питание  от батареи или от блока питания) или каждом интервале пробуждения (в режиме работы от батареи)."
                  }
                ]
              }
            },
            {
              "@from": "02",
              "@to": "02",
              "description": {
                "lang": [
                  {
                    "@xml:lang": "de",
                    "#text": "LED Anzeige zeigt die Temperatur fortlaufend an, nur im Batteriebetrieb"
                  },
                  {
                    "@xml:lang": "en",
                    "#text": "LED indicator indicates the temperature continuously, only in constant power\nmode"
                  },
                  {
                    "@xml:lang": "ru",
                    "#text": "Светодиодный индикатор постоянно отображает температуру. Этот режим доступен только при питании устройства  от блока питания."
                  }
                ]
              }
            }
          ]
        },
        {
          "@number": "73",
          "@type": "range",
          "@size": "2",
          "@default": "0000",
          "name": {
            "lang": [
              {
                "@xml:lang": "de",
                "#text": "Temperatur Messungs-Ausgleich"
              },
              {
                "@xml:lang": "en",
                "#text": "Temperature measurement compensation"
              },
              {
                "@xml:lang": "ru",
                "#text": "Компенсация при измерении температуры"
              }
            ]
          },
          "description": {
            "lang": [
              {
                "@xml:lang": "de",
                "#text": "Parameter speichert Temperaturwert, der vom Messwert addiert oder subtrahiert wird, um Messabweichungen auszugleichen"
              },
              {
                "@xml:lang": "en",
                "#text": "Parameter stores a temperature value to be added to or deducted from the current\r\ntemperature measured to compensate temperature deflection"
              },
              {
                "@xml:lang": "ru",
                "#text": "Этот параметр хранит в себе значение температуры, которая должна быть добавлена (или вычтена, в зависимости от знака) к температуре, измеряемой внутренним температурным датчиком. Эта коррекция необходима для того, чтобы учесть разницу температур воздуха на уровне пола и на уровне датчика. "
              }
            ]
          },
          "value": {
            "@from": "d8f0",
            "@to": "2710",
            "@unit": "x0,00°C",
            "description": {
              "lang": [
                {
                  "@xml:lang": "de"
                },
                {
                  "@xml:lang": "en"
                },
                {
                  "@xml:lang": "ru"
                }
              ]
            }
          }
        },
        {
          "@number": "74",
          "@type": "rangemapped",
          "@size": "1",
          "@default": "02",
          "name": {
            "lang": [
              {
                "@xml:lang": "de",
                "#text": "Alarm Frame für die 2. Assoziationsgruppe"
              },
              {
                "@xml:lang": "en",
                "#text": "Alarm frame sent to 2-nd Association Group activation"
              },
              {
                "@xml:lang": "ru",
                "#text": "Отключение сигнала тревоги для устройств из группы №2"
              }
            ]
          },
          "description": {
            "lang": [
              {
                "@xml:lang": "de",
                "#text": "Parameter legt fest, welche Sensoren einen Alarm an die 2. Assoziationsgruppe senden"
              },
              {
                "@xml:lang": "en",
                "#text": "parameter to device wich sensors send Alarm to 2. association group"
              },
              {
                "@xml:lang": "ru",
                "#text": "Настройка данного параметра позволяет включить отправку сигналов, оповещающих о вибрациях датчика (например, при его перемещениях) или о отжатии кнопки TMP (вскрытие). Сигналы тревоги для группы №2 при этом не отключаются."
              }
            ]
          },
          "value": [
            {
              "@from": "00",
              "@to": "00",
              "description": {
                "lang": [
                  {
                    "@xml:lang": "de",
                    "#text": "Schutzschalter-Alarme inaktiv"
                  },
                  {
                    "@xml:lang": "en",
                    "#text": "tamper alarms inactive"
                  },
                  {
                    "@xml:lang": "ru",
                    "#text": "Отключение оповещений о перемещении датчика и вскрытии"
                  }
                ]
              }
            },
            {
              "@from": "01",
              "@to": "01",
              "description": {
                "lang": [
                  {
                    "@xml:lang": "de",
                    "#text": "Manipulationsschutzschalter-Alarm aktiv"
                  },
                  {
                    "@xml:lang": "en",
                    "#text": "button tamper alarm active"
                  },
                  {
                    "@xml:lang": "ru",
                    "#text": "Включение оповещений о вскрытии датчика"
                  }
                ]
              }
            },
            {
              "@from": "02",
              "@to": "02",
              "description": {
                "lang": [
                  {
                    "@xml:lang": "de",
                    "#text": "Bewegungsschutzschalter-Alarm aktiv"
                  },
                  {
                    "@xml:lang": "en",
                    "#text": "movement tamper alarm active"
                  },
                  {
                    "@xml:lang": "ru",
                    "#text": "Включение оповещений о перемещении датчика"
                  }
                ]
              }
            },
            {
              "@from": "03",
              "@to": "03",
              "description": {
                "lang": [
                  {
                    "@xml:lang": "de",
                    "#text": "Manipulations- und Bewegungsschutzschalter aktiv"
                  },
                  {
                    "@xml:lang": "en",
                    "#text": "button and movement tampers alarm active"
                  },
                  {
                    "@xml:lang": "ru",
                    "#text": "Включение оповещений о перемещении датчика и вскрытии"
                  }
                ]
              }
            }
          ]
        },
        {
          "@number": "75",
          "@type": "range",
          "@size": "2",
          "@default": "0000",
          "name": {
            "lang": [
              {
                "@xml:lang": "de",
                "#text": "optische und akustische Alarmdauer"
              },
              {
                "@xml:lang": "en",
                "#text": "Visual and audible alarms duration"
              },
              {
                "@xml:lang": "ru",
                "#text": "Длительность звуковых и световых оповещений"
              }
            ]
          },
          "description": {
            "lang": [
              {
                "@xml:lang": "de",
                "#text": "Parameter legt fest, nach welcher Dauer der optische und akustische Alarm endet"
              },
              {
                "@xml:lang": "en",
                "#text": "parameter determines a time period after which visual and audible alarm will become “quiet”"
              },
              {
                "@xml:lang": "ru",
                "#text": "При желании пользователь может отключить звуковое оповещение датчика Fibaro Flood Sensor. Это обуславливается тем, что оповещение об аварийной ситуации может продолжаться в течение долгого периода времени, а своевременное отключение звуковых и световых сигналов позволит сохранить заряд батареи устройства. Значение этого параметра определяет длительность периода времени, после которого сигнализация датчика перейдет в «тихий» режим (оповещение об аварийной ситуации продолжается, однако устройство переходит в режим экономии заряда батареи). Звуковые и световые сигналы оповещения будут выключены по прошествии времени, указанном в параметре №76. Сигнал тревоги отключится сразу же как только будет устранена аварийная ситуацию.\r\nЗначение этого параметра 0 означает, что звуковые и световые сигналы оповещения не будут отключаться, пока существует аварийная ситуация. В режиме работы от батареи, в этом случае, устройство не будет переходить в спящий режим, что может значительно сократить заряд батареи. Значение этого параметра игнорируется, если значение параметра №2 равно 0."
              }
            ]
          },
          "value": {
            "@from": "0000",
            "@to": "7fff",
            "@unit": "s",
            "description": {
              "lang": [
                {
                  "@xml:lang": "de",
                  "#text": "Wert 0 bedeutet optischer und akustischer Alarm werden nicht beendet"
                },
                {
                  "@xml:lang": "en",
                  "#text": "value of 0 means visual and acoustic alarms are active indefinitely"
                },
                {
                  "@xml:lang": "ru",
                  "#text": "в секундах, 0 - тревога не будет отключаться"
                }
              ]
            }
          }
        },
        {
          "@number": "76",
          "@type": "range",
          "@size": "2",
          "@default": "0000",
          "name": {
            "lang": [
              {
                "@xml:lang": "de",
                "#text": "Alarm Frame/Basic Set Frame Zeit für erneutes Aussenden bei anhaltender Flut"
              },
              {
                "@xml:lang": "en",
                "#text": "Alarm frame / Basic Set frame retransmission time when retaining flood alarm"
              },
              {
                "@xml:lang": "ru",
                "#text": "Величина задержки перед повторной отправкой сигнала оповещения  (Alarm или Basic Set)"
              }
            ]
          },
          "description": {
            "lang": [
              {
                "@xml:lang": "de",
                "#text": "Parameter legt fest, nach welcher Zeit ein Alarm Frame erneut ausgesendet wird"
              },
              {
                "@xml:lang": "en",
                "#text": "Parameter determines a time period after which an alarm frame will be retransmitted"
              },
              {
                "@xml:lang": "ru",
                "#text": "Значение этого параметра определяет, через какой интервал времени по сети будет послан повторный сигнал оповещения об аварийной ситуации. Значение 0 означает, что сигнал оповещения посылаться не будет. В случае если интервал времени в этом параметре будет установлен меньшим, чем в параметре №75, устройство никогда не остановит передачу сигнала самостоятельно, оповещение будет работать всегда."
              }
            ]
          },
          "value": {
            "@from": "0000",
            "@to": "7fff",
            "@unit": "s",
            "description": {
              "lang": [
                {
                  "@xml:lang": "de",
                  "#text": "Wert 0 deaktiviert das erneute Aussenden des Alarms"
                },
                {
                  "@xml:lang": "en",
                  "#text": "value of 0 cancels an alarm frame retransmission"
                },
                {
                  "@xml:lang": "ru",
                  "#text": "в секундах, 0 - тревога не будет отправляться"
                }
              ]
            }
          }
        },
        {
          "@number": "77",
          "@type": "range",
          "@size": "1",
          "@default": "00",
          "name": {
            "lang": [
              {
                "@xml:lang": "de",
                "#text": "Flutsensor Funktion deaktivieren"
              },
              {
                "@xml:lang": "en",
                "#text": "Flood sensor functionality turned off"
              },
              {
                "@xml:lang": "ru",
                "#text": "Отключение функции обнаружения протечки"
              }
            ]
          },
          "description": {
            "lang": [
              {
                "@xml:lang": "de",
                "#text": "Aktivieren/Deaktivieren des internen Flutsensors. Schutzschalter und Temperatursensor bleiben aktiv"
              },
              {
                "@xml:lang": "en",
                "#text": "Allows for turning off the internal flood sensor. Tamper and built in temperature\r\nsensor will remain active."
              },
              {
                "@xml:lang": "ru",
                "#text": "Этот параметр позволяет настроить режим работы датчика протечки. Значение этого параметра не влияет на работу встроенного датчика перемещения и температурного датчика – они будут работать всегда."
              }
            ]
          },
          "value": [
            {
              "@from": "00",
              "@to": "00",
              "description": {
                "lang": [
                  {
                    "@xml:lang": "de",
                    "#text": "Normale Funktion des Flutsensors (Flut-Erkennung, Reaktionen)"
                  },
                  {
                    "@xml:lang": "en",
                    "#text": "Default flood sensor operation (flood detection, reactions)"
                  },
                  {
                    "@xml:lang": "ru",
                    "#text": "Функции обнаружения протечки работает"
                  }
                ]
              }
            },
            {
              "@from": "01",
              "@to": "01",
              "description": {
                "lang": [
                  {
                    "@xml:lang": "de",
                    "#text": "Flutsensor deaktiviert (Status im Controller ändert sich nicht, sendet keine Alarme und Basic Set Frames mit Änderungen des Flutstatus. Anzeige im Controller immer \"Aus\")"
                  },
                  {
                    "@xml:lang": "en",
                    "#text": "Built in flood sensor TURNED OFF (doesn’t change its state in the main\ncontroller, doesn’t send Alarms and Basic Set frames with flood state changes.\nAlways visible in the main controller as turned off)"
                  },
                  {
                    "@xml:lang": "ru",
                    "#text": "Встроенный датчик протечки отключен"
                  }
                ]
              }
            }
          ]
        }
      ]
    },
    "endpoints": {
      "endpoint": [
        {
          "@number": "2",
          "name": {
            "lang": [
              {
                "@xml:lang": "de"
              },
              {
                "@xml:lang": "en"
              },
              {
                "@xml:lang": "ru"
              }
            ]
          },
          "description": {
            "lang": [
              {
                "@xml:lang": "de"
              },
              {
                "@xml:lang": "en"
              },
              {
                "@xml:lang": "ru"
              }
            ]
          },
          "genericClass": {
            "@value": "21"
          },
          "specificClass": {
            "@value": "01"
          },
          "commandClass": [
            {
              "@id": "0020"
            },
            {
              "@id": "0031"
            }
          ]
        },
        {
          "@number": "1",
          "name": {
            "lang": [
              {
                "@xml:lang": "de"
              },
              {
                "@xml:lang": "en"
              },
              {
                "@xml:lang": "ru"
              }
            ]
          },
          "description": {
            "lang": [
              {
                "@xml:lang": "de"
              },
              {
                "@xml:lang": "en"
              },
              {
                "@xml:lang": "ru"
              }
            ]
          },
          "genericClass": {
            "@value": "20"
          },
          "specificClass": {
            "@value": "01"
          },
          "commandClass": [
            {
              "@id": "0030"
            },
            {
              "@id": "0020"
            }
          ]
        }
      ]
    },
    "resourceLinks": {
      "deviceImage": {
        "@url": "http://www.pepper1.net/zwavedb/uploads/resources/f79b4f7a9cdb77704b9903d483062e79b3628cb0.png"
      }
    }
  }
}