{
  "?xml": {
    "@version": "1.0",
    "@encoding": "utf-8"
  },
  "ZWaveDevice": {
    "@xmlns": "http://www.pepper1.net/zwavedb/xml-schemata/z-wave",
    "@schemaVersion": "2",
    "descriptorVersion": "1",
    "deviceData": {
      "manufacturerId": {
        "@value": "020e"
      },
      "productType": {
        "@value": "4754"
      },
      "productId": {
        "@value": "3038"
      },
      "libType": {
        "@value": "03"
      },
      "protoVersion": {
        "@value": "03"
      },
      "protoSubVersion": {
        "@value": "5f"
      },
      "appVersion": {
        "@value": "05"
      },
      "appSubVersion": {
        "@value": "09"
      },
      "basicClass": {
        "@value": "04"
      },
      "genericClass": {
        "@value": "11"
      },
      "specificClass": {
        "@value": "01"
      },
      "optional": {
        "@value": "true"
      },
      "listening": {
        "@value": "true"
      },
      "routing": {
        "@value": "true"
      },
      "beamSensor": "0"
    },
    "deviceDescription": {
      "description": {
        "lang": [
          {
            "@xml:lang": "de",
            "#text": "Dimmbare Z-Wave LED-Leuchte"
          },
          {
            "@xml:lang": "en",
            "#text": "Z-Wave dimmable E27 Light bulb"
          }
        ]
      },
      "wakeupNote": {
        "lang": [
          {
            "@xml:lang": "de"
          },
          {
            "@xml:lang": "en"
          }
        ]
      },
      "inclusionNote": {
        "lang": [
          {
            "@xml:lang": "de",
            "#text": "einfach Strom einschalten"
          },
          {
            "@xml:lang": "en",
            "#text": "Simple turn on/off the light"
          }
        ]
      },
      "productName": "ZBULB",
      "brandName": "Domitech",
      "productLine": "ZBULB",
      "productCode": "DOMEZBULB",
      "productVersion": "5.9"
    },
    "commandClasses": {
      "commandClass": [
        {
          "@id": "0020",
          "@inNIF": "false"
        },
        {
          "@id": "0026"
        },
        {
          "@id": "0027"
        },
        {
          "@id": "0059"
        },
        {
          "@id": "005a"
        },
        {
          "@id": "005e",
          "@version": "2"
        },
        {
          "@id": "0070"
        },
        {
          "@id": "0072",
          "@version": "2"
        },
        {
          "@id": "0073"
        },
        {
          "@id": "007a",
          "@version": "2"
        },
        {
          "@id": "0085",
          "@version": "2"
        },
        {
          "@id": "0086",
          "@version": "2"
        }
      ]
    },
    "assocGroups": {
      "assocGroup": {
        "@number": "1",
        "@maxNodes": "5",
        "description": {
          "lang": [
            {
              "@xml:lang": "de",
              "#text": "Lifeline"
            },
            {
              "@xml:lang": "en",
              "#text": "Lifeline"
            }
          ]
        }
      }
    },
    "configParams": {
      "configParam": {
        "@number": "1",
        "@type": "rangemapped",
        "@size": "1",
        "@default": "00",
        "name": {
          "lang": [
            {
              "@xml:lang": "de",
              "#text": "Status beim Wiedereinschalten der Leuchte"
            },
            {
              "@xml:lang": "en",
              "#text": "Status on turn on the bulb after turning off"
            }
          ]
        },
        "description": {
          "lang": [
            {
              "@xml:lang": "de",
              "#text": "Die Leuchte kann per Funk ausgeschaltet werden, auch wenn der Wandschalter in der An-Position bleibt Durch kurzes Ausschalten und Wieder-Einschalten kann die Leuchte dann auch vom Wandschalter aus eingeschaltet werden. Dieser Parameter definiert, wie die Lampe in diesem Falle leuchten soll"
            },
            {
              "@xml:lang": "en",
              "#text": "The Bulb can be turned off wirelessly while the powerswitch on the wall remains in on-position. The bulb can be turned back on from the wall switch by shortly turning of and then turning on again This parameter defines the status of the bulb after such an operation"
            }
          ]
        },
        "value": [
          {
            "@from": "00",
            "@to": "00",
            "description": {
              "lang": [
                {
                  "@xml:lang": "de",
                  "#text": "zurück zu 100 % Leuchstärke"
                },
                {
                  "@xml:lang": "en",
                  "#text": "back to 100 %"
                }
              ]
            }
          },
          {
            "@from": "01",
            "@to": "01",
            "description": {
              "lang": [
                {
                  "@xml:lang": "de",
                  "#text": "zurück zum letzten Dimmer-Niveau"
                },
                {
                  "@xml:lang": "en",
                  "#text": "back to last dimming level"
                }
              ]
            }
          }
        ]
      }
    },
    "resourceLinks": {
      "deviceImage": {
        "@url": "http://www.pepper1.net/zwavedb/uploads/resources/07b7bd4f01e6bb5d774e0187ba19d0c2073a7c6c.jpg"
      }
    }
  }
}