{
  "?xml": {
    "@version": "1.0",
    "@encoding": "utf-8"
  },
  "ZWaveDevice": {
    "@xmlns": "http://www.pepper1.net/zwavedb/xml-schemata/z-wave",
    "@schemaVersion": "2",
    "descriptorVersion": "1",
    "deviceData": {
      "manufacturerId": {
        "@value": "5254"
      },
      "productType": {
        "@value": "8201"
      },
      "productId": {
        "@value": "8021"
      },
      "libType": {
        "@value": "03"
      },
      "protoVersion": {
        "@value": "03"
      },
      "protoSubVersion": {
        "@value": "67"
      },
      "appVersion": {
        "@value": "00"
      },
      "appSubVersion": {
        "@value": "21"
      },
      "basicClass": {
        "@value": "04"
      },
      "genericClass": {
        "@value": "11"
      },
      "specificClass": {
        "@value": "01"
      },
      "optional": {
        "@value": "true"
      },
      "listening": {
        "@value": "true"
      },
      "routing": {
        "@value": "false"
      },
      "beamSensor": "0",
      "rfFrequency": "EU"
    },
    "deviceDescription": {
      "description": {
        "lang": {
          "@xml:lang": "en",
          "#text": "Z-Wave Dimming Switch Module"
        }
      },
      "wakeupNote": {
        "lang": {
          "@xml:lang": "en"
        }
      },
      "inclusionNote": {
        "lang": {
          "@xml:lang": "en",
          "#text": "Triple click the PROG button within 1 second."
        }
      },
      "productName": "ZDM-80SA ",
      "brandName": "Remotec",
      "productLine": "Z-Wave Home Automation",
      "productCode": "BW8021SA",
      "productVersion": "0.21"
    },
    "commandClasses": {
      "commandClass": [
        {
          "@id": "0020",
          "@controlled": "true"
        },
        {
          "@id": "0027"
        },
        {
          "@id": "0026",
          "@version": "2"
        },
        {
          "@id": "0070"
        },
        {
          "@id": "0085",
          "@version": "2"
        },
        {
          "@id": "0072"
        },
        {
          "@id": "002b"
        },
        {
          "@id": "002c"
        },
        {
          "@id": "0073"
        },
        {
          "@id": "0086"
        },
        {
          "@id": "0025"
        }
      ]
    },
    "assocGroups": {
      "assocGroup": [
        {
          "@number": "2",
          "@maxNodes": "4",
          "description": {
            "lang": {
              "@xml:lang": "en",
              "#text": ".. Dimmer mode: ZDM-80 will send out related dimming level e.g. 50% by basic set\r\ncommand to its association group automatically when ZDM-80 received the dimming\r\ncommand by local switch or wireless command e.g. 50%.\r\n.. Switch mode: ZDM-80 will send out related basic set command On (0xFF) or Off (0x00) to\r\nits association group automatically when ZDM-80 received On (0xFF) or Off (0x00)\r\ncommand by local switch or wireless command respectively.\r\n(Max. 4 nodes ID can be assigned to this association group)"
            }
          }
        },
        {
          "@number": "1",
          "@maxNodes": "1",
          "description": {
            "lang": {
              "@xml:lang": "en",
              "#text": "Association group_1 is used to report status change such as AUTO report to gateway."
            }
          }
        }
      ]
    },
    "configParams": {
      "configParam": [
        {
          "@number": "1",
          "@type": "constant",
          "@size": "1",
          "@default": "ff",
          "name": {
            "lang": {
              "@xml:lang": "en",
              "#text": "All On/All Of"
            }
          },
          "description": {
            "lang": {
              "@xml:lang": "en",
              "#text": "Choose if All On/All Off mode should be activated or deactivated."
            }
          },
          "value": [
            {
              "@from": "00",
              "@to": "00",
              "description": {
                "lang": {
                  "@xml:lang": "en",
                  "#text": "All On is not active,\r\nAll Off is not active"
                }
              }
            },
            {
              "@from": "01",
              "@to": "01",
              "description": {
                "lang": {
                  "@xml:lang": "en",
                  "#text": "All On is not active,\r\nAll Off active"
                }
              }
            },
            {
              "@from": "02",
              "@to": "02",
              "description": {
                "lang": {
                  "@xml:lang": "en",
                  "#text": "All On active,\r\nAll Off is not active"
                }
              }
            },
            {
              "@from": "ff",
              "@to": "ff",
              "description": {
                "lang": {
                  "@xml:lang": "en",
                  "#text": "All On active,\r\nAll Off active"
                }
              }
            }
          ]
        },
        {
          "@number": "5",
          "@type": "constant",
          "@size": "1",
          "@default": "01",
          "name": {
            "lang": {
              "@xml:lang": "en",
              "#text": "Switch state after power failure"
            }
          },
          "description": {
            "lang": {
              "@xml:lang": "en",
              "#text": "Switch returns to the last position\r\nsaved before power failure."
            }
          },
          "value": [
            {
              "@from": "00",
              "@to": "00",
              "description": {
                "lang": {
                  "@xml:lang": "en",
                  "#text": "Switch does not save\r\nthe state after power failure, it\r\nreturns to \"off\" position."
                }
              }
            },
            {
              "@from": "01",
              "@to": "01",
              "description": {
                "lang": {
                  "@xml:lang": "en",
                  "#text": "Switch saves its state\r\nbefore power failure."
                }
              }
            }
          ]
        },
        {
          "@number": "13",
          "@type": "constant",
          "@size": "1",
          "@default": "01",
          "name": {
            "lang": {
              "@xml:lang": "en",
              "#text": "Double click option"
            }
          },
          "description": {
            "lang": {
              "@xml:lang": "en",
              "#text": "Enable or disable double click function for maximum brightness level."
            }
          },
          "value": [
            {
              "@from": "00",
              "@to": "00",
              "description": {
                "lang": {
                  "@xml:lang": "en",
                  "#text": "Double click function\r\ndisabled."
                }
              }
            },
            {
              "@from": "01",
              "@to": "01",
              "description": {
                "lang": {
                  "@xml:lang": "en",
                  "#text": "Double click function\r\nenabled."
                }
              }
            }
          ]
        },
        {
          "@number": "17",
          "@type": "range",
          "@size": "1",
          "@default": "03",
          "name": {
            "lang": {
              "@xml:lang": "en",
              "#text": "Dimming time frame"
            }
          },
          "description": {
            "lang": {
              "@xml:lang": "en",
              "#text": "Sets the time of moving the Dimmer from 0%\r\nto max. dimming values. (The ZDM-80 will implement the\r\ndimming duration if received this\r\nparameter value from\r\ncontroller/gateway. Otherwise, the\r\nZDM-80 will implement the local\r\nparameter value)"
            }
          },
          "value": {
            "@from": "00",
            "@to": "05",
            "@unit": "sec",
            "description": {
              "lang": {
                "@xml:lang": "en",
                "#text": "Define time frame."
              }
            }
          }
        },
        {
          "@number": "18",
          "@type": "range",
          "@size": "1",
          "@default": "63",
          "name": {
            "lang": {
              "@xml:lang": "en",
              "#text": "Maximum Dimmer level control"
            }
          },
          "description": {
            "lang": {
              "@xml:lang": "en",
              "#text": "Define the upper dimming level. Higher percentages lead to higher brightness level."
            }
          },
          "value": {
            "@from": "02",
            "@to": "63",
            "@unit": "%",
            "description": {
              "lang": {
                "@xml:lang": "en",
                "#text": "Define dimming level."
              }
            }
          }
        },
        {
          "@number": "19",
          "@type": "range",
          "@size": "1",
          "@default": "0d",
          "name": {
            "lang": {
              "@xml:lang": "en",
              "#text": "Minimum Dimmer level control"
            }
          },
          "description": {
            "lang": {
              "@xml:lang": "en",
              "#text": "Define the lower dimming level. Lower percentages lead to lower brightness level."
            }
          },
          "value": {
            "@from": "01",
            "@to": "62",
            "@unit": "%",
            "description": {
              "lang": {
                "@xml:lang": "en",
                "#text": "Define dimming level."
              }
            }
          }
        }
      ]
    },
    "resourceLinks": {
      "deviceImage": {
        "@url": "http://www.pepper1.net/zwavedb/uploads/resources/671ee914a14f4c1c254143cafcb10d7bf79c318e.jpg"
      }
    }
  }
}